{
  "user": {
    "followers": 0,
    "following": 2,
    "public_repos": 3,
    "html_url": "https://github.com/Baretta-bit-byte"
  },
  "repos": [
    {
      "id": 1179020106,
      "name": "ogulcan-me",
      "description": "Personal Digital Garden & Portfolio — Next.js 16, Tailwind, Framer Motion, react-force-graph-2d",
      "html_url": "https://github.com/Baretta-bit-byte/ogulcan-me",
      "pushed_at": "2026-03-25T13:08:24Z",
      "stargazers_count": 1,
      "forks_count": 0,
      "language": "TypeScript"
    },
    {
      "id": 1161220846,
      "name": "c-exampleSolutions",
      "description": null,
      "html_url": "https://github.com/Baretta-bit-byte/c-exampleSolutions",
      "pushed_at": "2026-02-18T21:47:45Z",
      "stargazers_count": 1,
      "forks_count": 0,
      "language": "C"
    },
    {
      "id": 973456943,
      "name": "html-portfolio",
      "description": null,
      "html_url": "https://github.com/Baretta-bit-byte/html-portfolio",
      "pushed_at": "2025-04-27T18:32:51Z",
      "stargazers_count": 1,
      "forks_count": 0,
      "language": "HTML"
    }
  ],
  "lastPR": null,
  "contributions": null,
  "fetched_at": "2026-03-25T13:17:33.824Z"
}