{
  "profile": {
    "name": "Ogi",
    "followers": 6,
    "playlists": 77
  },
  "tracks": [
    {
      "id": "2Xhd1kYKj2aee7JR3nIlRe",
      "name": "Go",
      "artists": [
        "The Chemical Brothers",
        "Q-Tip"
      ],
      "album": "Born In The Echoes",
      "image": "https://i.scdn.co/image/ab67616d00001e025c75a31fa9fe49e63b4829ee",
      "url": "https://open.spotify.com/track/2Xhd1kYKj2aee7JR3nIlRe",
      "preview_url": null,
      "duration_ms": 260696,
      "genres": []
    },
    {
      "id": "3rVaOQfc8d1moQ47S5tHMw",
      "name": "Go",
      "artists": [
        "The Chemical Brothers",
        "Q-Tip"
      ],
      "album": "Go",
      "image": "https://i.scdn.co/image/ab6742d3000053b7e70a518e0f5efde17e2f7e52",
      "url": "https://open.spotify.com/track/3rVaOQfc8d1moQ47S5tHMw",
      "preview_url": null,
      "duration_ms": 220640,
      "genres": []
    },
    {
      "id": "3By9jCy6b4dv5XnlhvIWwx",
      "name": "Dies Irae",
      "artists": [
        "Giuseppe Verdi",
        "Carmen Giannattasio",
        "Veronica Simeoni",
        "Alxander Timchenko",
        "Carlo Colombara",
        "Yuri Temirkanov",
        "St. Petersburg Philharmonic Orchestra"
      ],
      "album": "Verdi Requiem",
      "image": "https://i.scdn.co/image/ab67616d00001e025abdabd1eeb2bdd287ad8ce9",
      "url": "https://open.spotify.com/track/3By9jCy6b4dv5XnlhvIWwx",
      "preview_url": null,
      "duration_ms": 134746,
      "genres": []
    },
    {
      "id": "0kYMwaQWABTkFff8AZjmYI",
      "name": "Hayloft II",
      "artists": [
        "Mother Mother"
      ],
      "album": "Inside (Deluxe)",
      "image": "https://i.scdn.co/image/ab67616d00001e02310a2e8ff7e84aa1cdbf04d2",
      "url": "https://open.spotify.com/track/0kYMwaQWABTkFff8AZjmYI",
      "preview_url": null,
      "duration_ms": 215040,
      "genres": []
    },
    {
      "id": "0j2T0R9dR9qdJYsB7ciXhf",
      "name": "Stronger",
      "artists": [
        "Kanye West"
      ],
      "album": "Graduation",
      "image": "https://i.scdn.co/image/ab67616d00001e0226f7f19c7f0381e56156c94a",
      "url": "https://open.spotify.com/track/0j2T0R9dR9qdJYsB7ciXhf",
      "preview_url": null,
      "duration_ms": 311866,
      "genres": []
    },
    {
      "id": "1v7L65Lzy0j0vdpRjJewt1",
      "name": "Lose Yourself",
      "artists": [
        "Eminem"
      ],
      "album": "Just Lose It",
      "image": "https://i.scdn.co/image/ab67616d00001e02b6ef2ebd34efb08cb76f6eec",
      "url": "https://open.spotify.com/track/1v7L65Lzy0j0vdpRjJewt1",
      "preview_url": null,
      "duration_ms": 322226,
      "genres": []
    },
    {
      "id": "2Efzv3bhKwgOuvJSEdBv8T",
      "name": "Bravo",
      "artists": [
        "Barbara Pravi"
      ],
      "album": "Bravo",
      "image": "https://i.scdn.co/image/ab6742d3000053b798340bc0f2a66e1e4921cd2d",
      "url": "https://open.spotify.com/track/2Efzv3bhKwgOuvJSEdBv8T",
      "preview_url": null,
      "duration_ms": 203450,
      "genres": []
    },
    {
      "id": "2OQJKTtrH482waGFmOfJni",
      "name": "We Own It (Fast & Furious)",
      "artists": [
        "2 Chainz",
        "Wiz Khalifa"
      ],
      "album": "B.O.A.T.S. II #METIME (Deluxe)",
      "image": "https://i.scdn.co/image/ab67616d00001e02b4366694590f7164fad21fc7",
      "url": "https://open.spotify.com/track/2OQJKTtrH482waGFmOfJni",
      "preview_url": null,
      "duration_ms": 227906,
      "genres": []
    },
    {
      "id": "2SL6oP2YAEQbqsrkOzRGO4",
      "name": "Venom - Music From The Motion Picture",
      "artists": [
        "Eminem"
      ],
      "album": "Kamikaze",
      "image": "https://i.scdn.co/image/ab67616d00001e02e4073def0c03a91e3fceaf73",
      "url": "https://open.spotify.com/track/2SL6oP2YAEQbqsrkOzRGO4",
      "preview_url": null,
      "duration_ms": 269554,
      "genres": []
    },
    {
      "id": "4gvIHkUkkXlfuyZvmVVLl4",
      "name": "Face Off",
      "artists": [
        "Tech N9ne",
        "Joey Cool",
        "King Iso",
        "Dwayne Johnson"
      ],
      "album": "Face Off",
      "image": "https://i.scdn.co/image/ab6742d3000053b7faead4d3950b84e03ccec582",
      "url": "https://open.spotify.com/track/4gvIHkUkkXlfuyZvmVVLl4",
      "preview_url": null,
      "duration_ms": 247466,
      "genres": []
    },
    {
      "id": "4xkOaSrkexMciUUogZKVTS",
      "name": "Till I Collapse",
      "artists": [
        "Eminem",
        "Nate Dogg"
      ],
      "album": "The Eminem Show",
      "image": "https://i.scdn.co/image/ab67616d00001e026ca5c90113b30c3c43ffb8f4",
      "url": "https://open.spotify.com/track/4xkOaSrkexMciUUogZKVTS",
      "preview_url": null,
      "duration_ms": 297786,
      "genres": []
    },
    {
      "id": "5zsHmE2gO3RefVsPyw2e3T",
      "name": "What's Up Danger (with Black Caviar)",
      "artists": [
        "Blackway",
        "Black Caviar"
      ],
      "album": "Spider-Man: Into the Spider-Verse (Soundtrack From & Inspired by the Motion Picture)",
      "image": "https://i.scdn.co/image/ab67616d00001e02e2e352d89826aef6dbd5ff8f",
      "url": "https://open.spotify.com/track/5zsHmE2gO3RefVsPyw2e3T",
      "preview_url": null,
      "duration_ms": 222306,
      "genres": []
    }
  ],
  "recently_played": [
    {
      "id": "7q9vs73hCbPuFLF4o6nvih",
      "name": "Six Days - Radio Edit",
      "artists": [
        "DJ Shadow"
      ],
      "album": "Six Days",
      "image": "https://i.scdn.co/image/ab67616d00001e02201b70d118d7b23f19040f11",
      "url": "https://open.spotify.com/track/7q9vs73hCbPuFLF4o6nvih",
      "duration_ms": 218133,
      "played_at": "2026-06-26T15:40:25.972Z"
    },
    {
      "id": "3Vuv2DNWcexDwda2auaWzj",
      "name": "Another Brick in the Wall, Pt. 2",
      "artists": [
        "Pink Floyd"
      ],
      "album": "Another Brick in the Wall, Pt. 2",
      "image": "https://i.scdn.co/image/ab6742d3000053b705fe4dba4083b20b24c949ae",
      "url": "https://open.spotify.com/track/3Vuv2DNWcexDwda2auaWzj",
      "duration_ms": 198400,
      "played_at": "2026-06-26T15:38:49.584Z"
    },
    {
      "id": "3qVKp0bGG2uEkrkMOtwb5F",
      "name": "Fitzpleasure",
      "artists": [
        "alt-J"
      ],
      "album": "An Awesome Wave",
      "image": "https://i.scdn.co/image/ab67616d00001e021e1ca90cd8fdbb0ac890a926",
      "url": "https://open.spotify.com/track/3qVKp0bGG2uEkrkMOtwb5F",
      "duration_ms": 219400,
      "played_at": "2026-06-26T15:35:30.035Z"
    },
    {
      "id": "5RCo8gwmcHB8cRyKrOVOOk",
      "name": "Bestie, Move On",
      "artists": [
        "Jea Mira"
      ],
      "album": "girl's notes",
      "image": "https://i.scdn.co/image/ab67616d00001e02b1bbb004319f22a08464e3c0",
      "url": "https://open.spotify.com/track/5RCo8gwmcHB8cRyKrOVOOk",
      "duration_ms": 211581,
      "played_at": "2026-06-26T15:31:50.210Z"
    },
    {
      "id": "6Wqei6kTTJkf7YH6VXqWQg",
      "name": "Take Me To Church",
      "artists": [
        "Hozier"
      ],
      "album": "Take Me To Church",
      "image": "https://i.scdn.co/image/ab6742d3000053b79c9c824f574727112b7b6a41",
      "url": "https://open.spotify.com/track/6Wqei6kTTJkf7YH6VXqWQg",
      "duration_ms": 240288,
      "played_at": "2026-06-26T15:28:18.221Z"
    },
    {
      "id": "2JGOtqIA0i5aFkK03Ktt8Z",
      "name": "Nocturne",
      "artists": [
        "Bor Pro"
      ],
      "album": "Subliminal",
      "image": "https://i.scdn.co/image/ab67616d00001e021a6f643a47cf49d5c45f3760",
      "url": "https://open.spotify.com/track/2JGOtqIA0i5aFkK03Ktt8Z",
      "duration_ms": 168045,
      "played_at": "2026-06-26T15:24:16.629Z"
    },
    {
      "id": "2IWtloZYQDcP8Ashwx8QEF",
      "name": "Black Out Days",
      "artists": [
        "Phantogram"
      ],
      "album": "Voices",
      "image": "https://i.scdn.co/image/ab67616d00001e024a02353678a4f62a9d2e3d2b",
      "url": "https://open.spotify.com/track/2IWtloZYQDcP8Ashwx8QEF",
      "duration_ms": 227160,
      "played_at": "2026-06-26T15:21:28.113Z"
    },
    {
      "id": "3byTF0jZuyKGYJUE55Kft1",
      "name": "Stressed Out",
      "artists": [
        "Twenty One Pilots"
      ],
      "album": "Stressed Out",
      "image": "https://i.scdn.co/image/ab6742d3000053b7f443a750d30f352507414275",
      "url": "https://open.spotify.com/track/3byTF0jZuyKGYJUE55Kft1",
      "duration_ms": 218346,
      "played_at": "2026-06-26T15:17:40.477Z"
    },
    {
      "id": "60SvhHtwefT0e2G7i7kOH3",
      "name": "New Gold (feat. Tame Impala and Bootie Brown)",
      "artists": [
        "Gorillaz",
        "Tame Impala",
        "Bootie Brown"
      ],
      "album": "Cracker Island",
      "image": "https://i.scdn.co/image/ab67616d00001e0219707804f73dc50f7a29cd86",
      "url": "https://open.spotify.com/track/60SvhHtwefT0e2G7i7kOH3",
      "duration_ms": 215149,
      "played_at": "2026-06-26T15:14:00.580Z"
    },
    {
      "id": "4uvg9atUhMUhKSTxg6cg6H",
      "name": "Roi",
      "artists": [
        "Videoclub"
      ],
      "album": "Roi",
      "image": "https://i.scdn.co/image/ab6742d3000053b7b359921828194388d13e72b6",
      "url": "https://open.spotify.com/track/4uvg9atUhMUhKSTxg6cg6H",
      "duration_ms": 230080,
      "played_at": "2026-06-26T15:10:24.958Z"
    }
  ],
  "fetched_at": "2026-06-26T17:45:25.210Z"
}